{
    "parent": "shroomhearth:_shroomhearth_guide",
    "display": {
        "icon": {
            "id": "minecraft:mycelium"
        },
        "title": "The Hearth",
        "description": "Visit the Hearth Island",
        "background": "minecraft:block/mushroom_stem",
        "frame": "task"
    },
    "criteria": {
        "hearth_island": {
            "trigger": "minecraft:location",
            "conditions": {
                "player": {
                    "location": {
                        "dimension": "minecraft:overworld",
                        "position": {
                            "x": {
                                "min": 999999,
                                "max": 999999
                            },
                            "z": {
                                "min": 999999,
                                "max": 999999
                            }
                        }
                    }
                }
            }
        }
    }
}