{
    "condition": "minecraft:inverted",
    "term": {
        "condition": "minecraft:entity_properties",
        "entity": "this",
        "predicate": {
            "minecraft:team": "ender_dragon",
            "minecraft:entity_type": "#shroomhearth:ender_dragon/dragon_thralls",
            "minecraft:location": {
                "dimension": "minecraft:the_end",
                "position": {
                    "x": {
                        "min": -200,
                        "max": 200
                    },
                    "z": {
                        "min": -200,
                        "max": 200
                    }
                }
            },
            "minecraft:passenger": {}
        }
    }
}