{
  "parent": "minecraft:recipes/root",
  "rewards": {
    "recipes": [
      "bityard:copper/oxidize_cut_copper"
    ]
  },
  "criteria": {
    "has_block": {
      "trigger": "minecraft:inventory_changed",
      "conditions": {
        "items": [
          {
            "item": "minecraft:cut_copper"
          }
        ]
      }
    },
    "has_magma_cream": {
      "trigger": "minecraft:inventory_changed",
      "conditions": {
        "items": [
          {
            "item": "minecraft:magma_cream"
          }
        ]
      }
    },
    "has_recipe": {
      "trigger": "minecraft:recipe_unlocked",
      "conditions": {
        "recipe": "bityard:copper/oxidize_cut_copper"
      }
    }
  },
  "requirements": [
    [
      "has_block",
      "has_magma_cream",
      "has_recipe"
    ]
  ]
}