{
    "pools": [
        {
            "rolls": 1,
            "entries": [
                {
                    "type": "item",
                    "name": "minecraft:diamond_axe",
                    "weight": 1,
                    "functions": [
                        {
                            "function": "minecraft:set_components",
                            "components": {
                                "minecraft:item_name": {
                                    "translate": "hallow_vale.bleeding_tooth",
                                    "fallback": "Bleeding Tooth"
                                },
                                "minecraft:item_model": "shroomhearth:bleeding_tooth",
                                "minecraft:rarity": "epic",
                                "minecraft:enchantments": {
                                    "relics:blistering_spores": 1
                                },
                                "minecraft:lore": [
                                    {
                                        "text": "Embedded with the mycelium of an invasive, arboreal fungus."
                                    },
                                    {
                                        "text": "Attacks inflict additional damage after a short delay."
                                    }
                                ],
                                "minecraft:custom_data": {
                                    "spore": "bleeding_tooth"
                                }
                            }
                        }
                    ]
                }
            ]
        }
    ]
}